pvplr/SDT_data_handler.py
pvplr/bootstrap_uncertainty.py
pvplr/feature_correction.py
pvplr/model_comparison.py
pvplr/plr_determination.py
pvplr/regions_to_test.py
pvplr/testing_synthetic_data.py
pvplr/util.py
pvplr/testing/Test_36.1_-107.61.csv
pvplr/testing/Test_38.49_-108.38.csv
pvplr/testing/Test_39.17_-103.68.csv
pvplr/testing/Test_39.74_-107.82.csv
pvplr/testing/Test_39.86_-107.43.csv
pvplr/testing/synthetic_data_generation.py
pvplr-2024.7.29.dist-info/LICENSE
pvplr-2024.7.29.dist-info/METADATA
pvplr-2024.7.29.dist-info/WHEEL
pvplr-2024.7.29.dist-info/top_level.txt
pvplr-2024.7.29.dist-info/RECORD
