Metadata-Version: 2.1
Name: pvplr
Version: 2024.7.29
Summary: PV PLR analysis
License: BSD-2-Clause
License-File: LICENSE
Requires-Dist: numpy
Requires-Dist: pandas
Requires-Dist: matplotlib
Requires-Dist: scipy
